pytdv2/TrustedDevice.py
pytdv2/TrustedDeviceImpl.py
pytdv2/__init__.py
pytdv2/device.py
pytdv2/fazpass.py
pytdv2/utils.py
pytdv2-0.3.dist-info/LICENSE
pytdv2-0.3.dist-info/METADATA
pytdv2-0.3.dist-info/WHEEL
pytdv2-0.3.dist-info/top_level.txt
pytdv2-0.3.dist-info/RECORD
