Metadata-Version: 2.1
Name: pytdv2
Version: 0.3
Summary: Official python library for trusted device from fazpass company
Home-page: https://github.com/fazpass-sdk/python-trusted-device-v2
Author: fazpass
Author-email: info.fazpass@gmail.com
License: MIT
Classifier: Programming Language :: Python :: 3
Classifier: Programming Language :: Python :: 3.6
Classifier: Programming Language :: Python :: 3.7
Classifier: Programming Language :: Python :: 3.8
Requires-Python: >=3.4
License-File: LICENSE
Requires-Dist: pycryptodome
